email_reader/__init__.py
email_reader/encrypt_decrypt.py
email_reader/encryption_key.txt
email_reader/read_email.py
email_reader-1.0.23.data/data/data/encryption_key.txt
email_reader-1.0.23.dist-info/METADATA
email_reader-1.0.23.dist-info/WHEEL
email_reader-1.0.23.dist-info/top_level.txt
email_reader-1.0.23.dist-info/RECORD
